deepwork/__init__.py
deepwork/cli/__init__.py
deepwork/cli/hook.py
deepwork/cli/install.py
deepwork/cli/main.py
deepwork/cli/rules.py
deepwork/cli/sync.py
deepwork/core/__init__.py
deepwork/core/adapters.py
deepwork/core/command_executor.py
deepwork/core/detector.py
deepwork/core/doc_spec_parser.py
deepwork/core/generator.py
deepwork/core/hooks_syncer.py
deepwork/core/parser.py
deepwork/core/pattern_matcher.py
deepwork/core/rules_parser.py
deepwork/core/rules_queue.py
deepwork/hooks/README.md
deepwork/hooks/__init__.py
deepwork/hooks/check_version.sh
deepwork/hooks/claude_hook.sh
deepwork/hooks/gemini_hook.sh
deepwork/hooks/rules_check.py
deepwork/hooks/wrapper.py
deepwork/schemas/__init__.py
deepwork/schemas/doc_spec_schema.py
deepwork/schemas/job_schema.py
deepwork/schemas/rules_schema.py
deepwork/standard_jobs/deepwork_jobs/AGENTS.md
deepwork/standard_jobs/deepwork_jobs/job.yml
deepwork/standard_jobs/deepwork_jobs/make_new_job.sh
deepwork/standard_jobs/deepwork_jobs/doc_specs/job_spec.md
deepwork/standard_jobs/deepwork_jobs/steps/define.md
deepwork/standard_jobs/deepwork_jobs/steps/implement.md
deepwork/standard_jobs/deepwork_jobs/steps/learn.md
deepwork/standard_jobs/deepwork_jobs/steps/review_job_spec.md
deepwork/standard_jobs/deepwork_jobs/steps/supplemental_file_references.md
deepwork/standard_jobs/deepwork_jobs/templates/agents.md.template
deepwork/standard_jobs/deepwork_jobs/templates/doc_spec.md.example
deepwork/standard_jobs/deepwork_jobs/templates/doc_spec.md.template
deepwork/standard_jobs/deepwork_jobs/templates/job.yml.example
deepwork/standard_jobs/deepwork_jobs/templates/job.yml.template
deepwork/standard_jobs/deepwork_jobs/templates/step_instruction.md.example
deepwork/standard_jobs/deepwork_jobs/templates/step_instruction.md.template
deepwork/standard_jobs/deepwork_rules/job.yml
deepwork/standard_jobs/deepwork_rules/hooks/capture_prompt_work_tree.sh
deepwork/standard_jobs/deepwork_rules/hooks/global_hooks.yml
deepwork-0.5.1.dist-info/METADATA
deepwork-0.5.1.dist-info/WHEEL
deepwork-0.5.1.dist-info/entry_points.txt
deepwork-0.5.1.dist-info/licenses/LICENSE.md
deepwork-0.5.1.dist-info/RECORD
