Metadata-Version: 2.4
Name: deepwork
Version: 0.5.1
Summary: Framework for enabling AI agents to perform complex, multi-step work tasks
Project-URL: Homepage, https://github.com/deepwork/deepwork
Project-URL: Documentation, https://github.com/deepwork/deepwork#readme
Project-URL: Repository, https://github.com/deepwork/deepwork
Project-URL: Issues, https://github.com/deepwork/deepwork/issues
Author: DeepWork Contributors
License: Business Source License 1.1
License-File: LICENSE.md
Keywords: agents,ai,automation,cli,workflow
Classifier: Development Status :: 3 - Alpha
Classifier: Intended Audience :: Developers
Classifier: License :: Other/Proprietary License
Classifier: Programming Language :: Python :: 3
Classifier: Programming Language :: Python :: 3.11
Classifier: Programming Language :: Python :: 3.12
Classifier: Topic :: Software Development :: Libraries :: Application Frameworks
Requires-Python: >=3.11
Requires-Dist: click>=8.1.0
Requires-Dist: gitpython>=3.1.0
Requires-Dist: jinja2>=3.1.0
Requires-Dist: jsonschema>=4.17.0
Requires-Dist: pyyaml>=6.0
Requires-Dist: rich>=13.0.0
Provides-Extra: dev
Requires-Dist: mypy>=1.0; extra == 'dev'
Requires-Dist: pytest-cov>=4.0; extra == 'dev'
Requires-Dist: pytest-mock>=3.10; extra == 'dev'
Requires-Dist: pytest>=7.0; extra == 'dev'
Requires-Dist: ruff>=0.1.0; extra == 'dev'
Requires-Dist: types-pyyaml; extra == 'dev'
